{"lastUsed":1650462029706,"path":"C:\/work\/eclipse-workspace","projectCount":5,"recentFiles":[{"path":"\/Mavenjava","parentWorkspace":"C:\/Users\/ejee\/eclipse-workspace","name":"testng.xml","lastModified":1650029607518,"locationURI":"file:\/C:\/Users\/ejee\/eclipse-workspace\/Mavenjava\/testng.xml"},{"path":"\/TestNGTutorial\/src\/test","parentWorkspace":"C:\/Users\/ejee\/eclipse-workspace","name":"day4.java","lastModified":1649941001280,"locationURI":"file:\/C:\/Users\/ejee\/eclipse-workspace\/TestNGTutorial\/src\/test\/day4.java"},{"path":"\/AppiumFramework\/src\/test\/java\/practise\/AppiumFramework","parentWorkspace":"C:\/work\/eclipse-workspace","name":"ApiDemoTest.java","lastModified":1650282979106,"locationURI":"file:\/C:\/work\/eclipse-workspace\/AppiumFramework\/src\/test\/java\/practise\/AppiumFramework\/ApiDemoTest.java"},{"path":"\/AppiumFramework\/src\/main\/java\/pageObjects","parentWorkspace":"C:\/work\/eclipse-workspace","name":"Preferences.java","lastModified":1650210862775,"locationURI":"file:\/C:\/work\/eclipse-workspace\/AppiumFramework\/src\/main\/java\/pageObjects\/Preferences.java"},{"path":"\/TestNGTutorial\/src\/test","parentWorkspace":"C:\/Users\/ejee\/eclipse-workspace","name":"day2.java","lastModified":1649854342300,"locationURI":"file:\/C:\/Users\/ejee\/eclipse-workspace\/TestNGTutorial\/src\/test\/day2.java"},{"path":"\/AppiumFramework\/src\/main\/java\/pageObjects","parentWorkspace":"C:\/work\/eclipse-workspace","name":"FormPage.java","lastModified":1650210788299,"locationURI":"file:\/C:\/work\/eclipse-workspace\/AppiumFramework\/src\/main\/java\/pageObjects\/FormPage.java"},{"path":"\/Tutorial","parentWorkspace":"C:\/Users\/ejee\/eclipse-workspace","name":"pom.xml","lastModified":1649411170640},{"path":"\/TestNGTutorial","parentWorkspace":"C:\/Users\/ejee\/eclipse-workspace","name":"testng.xml","lastModified":1649953316452,"locationURI":"file:\/C:\/Users\/ejee\/eclipse-workspace\/TestNGTutorial\/testng.xml"},{"path":"\/AppiumFramework\/src\/test\/java\/practise\/AppiumFramework","parentWorkspace":"C:\/work\/eclipse-workspace","name":"Ecommerce_tc_4.java","lastModified":1650280891926,"locationURI":"file:\/C:\/work\/eclipse-workspace\/AppiumFramework\/src\/test\/java\/practise\/AppiumFramework\/Ecommerce_tc_4.java"},{"path":"\/Mavenjava\/src\/test\/java\/qaclickacademy","parentWorkspace":"C:\/Users\/ejee\/eclipse-workspace","name":"RestAPITest.java","lastModified":1650027613131,"locationURI":"file:\/C:\/Users\/ejee\/eclipse-workspace\/Mavenjava\/src\/test\/java\/qaclickacademy\/RestAPITest.java"},{"path":"\/Mavenjava","parentWorkspace":"C:\/Users\/ejee\/eclipse-workspace","name":"pom.xml","lastModified":1650190734534,"locationURI":"file:\/C:\/Users\/ejee\/eclipse-workspace\/Mavenjava\/pom.xml"},{"path":"\/AppiumFramework\/src\/main\/java\/practise\/AppiumFramework","parentWorkspace":"C:\/work\/eclipse-workspace","name":"base.java","lastModified":1650287415424,"locationURI":"file:\/C:\/work\/eclipse-workspace\/AppiumFramework\/src\/main\/java\/practise\/AppiumFramework\/base.java"},{"path":"\/Mavenjava\/src\/test\/java\/qaclickacademy","parentWorkspace":"C:\/Users\/ejee\/eclipse-workspace","name":"AppiumTest.java","lastModified":1650028557069,"locationURI":"file:\/C:\/Users\/ejee\/eclipse-workspace\/Mavenjava\/src\/test\/java\/qaclickacademy\/AppiumTest.java"},{"path":"\/TestNGTutorial\/src\/test","parentWorkspace":"C:\/Users\/ejee\/eclipse-workspace","name":"Listeners.java","lastModified":1649951563704,"locationURI":"file:\/C:\/Users\/ejee\/eclipse-workspace\/TestNGTutorial\/src\/test\/Listeners.java"},{"path":"\/TestNGTutorial","parentWorkspace":"C:\/Users\/ejee\/eclipse-workspace","name":"testng2.xml","lastModified":1649838131493,"locationURI":"file:\/C:\/Users\/ejee\/eclipse-workspace\/TestNGTutorial\/testng2.xml"},{"path":"\/AppiumFramework\/src\/main\/java\/resources","parentWorkspace":"C:\/work\/eclipse-workspace","name":"ExtentReporterNG.java","lastModified":1650441157864,"locationURI":"file:\/C:\/work\/eclipse-workspace\/AppiumFramework\/src\/main\/java\/resources\/ExtentReporterNG.java"},{"path":"\/AppiumFramework\/src\/main\/java\/resources","parentWorkspace":"C:\/work\/eclipse-workspace","name":"Listeners.java","lastModified":1650280891926,"locationURI":"file:\/C:\/work\/eclipse-workspace\/AppiumFramework\/src\/main\/java\/resources\/Listeners.java"},{"path":"\/Tutorial\/src\/pageObjects","parentWorkspace":"C:\/work\/eclipse-workspace","name":"HomePage.java","lastModified":1650105345989,"locationURI":"file:\/C:\/work\/eclipse-workspace\/Tutorial\/src\/pageObjects\/HomePage.java"},{"path":"\/AppiumFramework","parentWorkspace":"C:\/work\/eclipse-workspace","name":"pom.xml","lastModified":1650287415427,"locationURI":"file:\/C:\/work\/eclipse-workspace\/AppiumFramework\/pom.xml"},{"path":"\/AppiumFramework\/src\/main\/java\/practise\/AppiumFramework","parentWorkspace":"C:\/work\/eclipse-workspace","name":"TestData.java","lastModified":1650282868999,"locationURI":"file:\/C:\/work\/eclipse-workspace\/AppiumFramework\/src\/main\/java\/practise\/AppiumFramework\/TestData.java"},{"path":"\/TestNGTutorial\/src\/test","parentWorkspace":"C:\/Users\/ejee\/eclipse-workspace","name":"day3.java","lastModified":1649948994344,"locationURI":"file:\/C:\/Users\/ejee\/eclipse-workspace\/TestNGTutorial\/src\/test\/day3.java"},{"path":"\/Tutorial\/src","parentWorkspace":"C:\/work\/eclipse-workspace","name":"base.java","lastModified":1650102841275,"locationURI":"file:\/C:\/work\/eclipse-workspace\/Tutorial\/src\/base.java"},{"path":"\/TestNGTutorial","parentWorkspace":"C:\/Users\/ejee\/eclipse-workspace","name":"testng3.xml","lastModified":1649854649488,"locationURI":"file:\/C:\/Users\/ejee\/eclipse-workspace\/TestNGTutorial\/testng3.xml"},{"path":"\/TestNGTutorial\/src\/test","parentWorkspace":"C:\/Users\/ejee\/eclipse-workspace","name":"day1.java","lastModified":1649951492874,"locationURI":"file:\/C:\/Users\/ejee\/eclipse-workspace\/TestNGTutorial\/src\/test\/day1.java"},{"path":"\/AppiumFramework\/src\/main\/java\/pageObjects","parentWorkspace":"C:\/work\/eclipse-workspace","name":"HomePage.java","lastModified":1650210828312,"locationURI":"file:\/C:\/work\/eclipse-workspace\/AppiumFramework\/src\/main\/java\/pageObjects\/HomePage.java"},{"path":"\/AppiumFramework\/src\/main\/java\/practise\/AppiumFramework","parentWorkspace":"C:\/work\/eclipse-workspace","name":"Utilities.java","lastModified":1650211232613,"locationURI":"file:\/C:\/work\/eclipse-workspace\/AppiumFramework\/src\/main\/java\/practise\/AppiumFramework\/Utilities.java"},{"path":"\/AppiumFramework","parentWorkspace":"C:\/work\/eclipse-workspace","name":"testng.xml","lastModified":1650281850161,"locationURI":"file:\/C:\/work\/eclipse-workspace\/AppiumFramework\/testng.xml"},{"path":"\/AppiumFramework\/src\/main\/java\/practise\/AppiumFramework","parentWorkspace":"C:\/work\/eclipse-workspace","name":"global.properties","lastModified":1650287437114,"locationURI":"file:\/C:\/work\/eclipse-workspace\/AppiumFramework\/src\/main\/java\/practise\/AppiumFramework\/global.properties"},{"path":"\/AppiumFramework\/test-output","parentWorkspace":"C:\/work\/eclipse-workspace","name":"testng-results.xml","lastModified":1650280891686,"locationURI":"file:\/C:\/work\/eclipse-workspace\/AppiumFramework\/test-output\/testng-results.xml"},{"path":"\/Tutorial\/src","parentWorkspace":"C:\/work\/eclipse-workspace","name":"basic.java","lastModified":1650105345996,"locationURI":"file:\/C:\/work\/eclipse-workspace\/Tutorial\/src\/basic.java"},{"path":"\/Tutorial\/src\/pageObjects","parentWorkspace":"C:\/work\/eclipse-workspace","name":"Preferences.java","lastModified":1650105345992,"locationURI":"file:\/C:\/work\/eclipse-workspace\/Tutorial\/src\/pageObjects\/Preferences.java"},{"path":"\/AppiumFramework\/src\/main\/java\/pageObjects","parentWorkspace":"C:\/work\/eclipse-workspace","name":"CheckoutPage.java","lastModified":1650210725878,"locationURI":"file:\/C:\/work\/eclipse-workspace\/AppiumFramework\/src\/main\/java\/pageObjects\/CheckoutPage.java"},{"path":"\/Mavenjava\/src\/test\/java\/qaclickacademy","parentWorkspace":"C:\/Users\/ejee\/eclipse-workspace","name":"SeleniumTest.java","lastModified":1650027616223,"locationURI":"file:\/C:\/Users\/ejee\/eclipse-workspace\/Mavenjava\/src\/test\/java\/qaclickacademy\/SeleniumTest.java"}]}